{"type":"BufferGeometry","uuid":"14DA7A37-D050-4D51-AE01-FAF302CA9C77","data":{"attributes":{"position":{"type":"Float32Array","itemSize":3,"normalized":false,"array":[]},"normal":{"type":"Float32Array","itemSize":3,"normalized":false,"array":[]},"color":{"type":"Float32Array","itemSize":3,"normalized":false,"array":[]},"uv":{"type":"Float32Array","itemSize":2,"normalized":false,"array":[]},"ao":{"type":"Float32Array","itemSize":1,"normalized":false,"array":[]},"blocklight":{"type":"Float32Array","itemSize":1,"normalized":false,"array":[]},"sunlight":{"type":"Float32Array","itemSize":1,"normalized":false,"array":[]}},"groups":[]}}